tsutsumu/__init__.py
tsutsumu/__main__.py
tsutsumu/bundle.py
tsutsumu/debug.py
tsutsumu/maker.py
tsutsumu-0.1.0.dist-info/entry_points.txt
tsutsumu-0.1.0.dist-info/WHEEL
tsutsumu-0.1.0.dist-info/METADATA
tsutsumu-0.1.0.dist-info/RECORD
