Metadata-Version: 2.1
Name: tsutsumu
Version: 0.1.0
Summary: Python module bundles
Keywords: bundler,source code bundle,module bundle
Author-email: Robert Grimm <rgrimm@alum.mit.edu>
Requires-Python: >=3.7
Classifier: Development Status :: 4 - Beta
Classifier: Environment :: Console
Classifier: Intended Audience :: Developers
Classifier: Intended Audience :: Education
Classifier: Intended Audience :: Information Technology
Classifier: License :: OSI Approved :: Apache Software License
Classifier: Operating System :: OS Independent
Classifier: Programming Language :: Python :: 3.7
Classifier: Programming Language :: Python :: 3.8
Classifier: Programming Language :: Python :: 3.9
Classifier: Programming Language :: Python :: 3.10
Classifier: Programming Language :: Python :: 3.11
Classifier: Programming Language :: Python :: 3.12
Classifier: Topic :: File Formats
Classifier: Topic :: Home Automation
Classifier: Topic :: Internet
Classifier: Topic :: Software Development :: Build Tools
Classifier: Topic :: Software Development :: Code Generators
Classifier: Topic :: System :: Installation/Setup
Classifier: Topic :: System :: Software Distribution
Classifier: Topic :: Utilities
Requires-Dist: mypy ; extra == "dev"
Requires-Dist: flit ; extra == "dev"
Requires-Dist: vermin ; extra == "dev"
Project-URL: Repository, https://github.com/apparebit/tsutsumu
Provides-Extra: dev
